{
  "version": "0.1.0",
  "name": "raffle_rewards_program",
  "instructions": [
    {
      "name": "initializeGlobalTreasury",
      "accounts": [
        {
          "name": "payer",
          "isMut": true,
          "isSigner": true
        },
        {
          "name": "authority",
          "isMut": false,
          "isSigner": false
        },
        {
          "name": "globalTreasurySigner",
          "isMut": true,
          "isSigner": false
        },
        {
          "name": "systemProgram",
          "isMut": false,
          "isSigner": false
        }
      ],
      "args": []
    },
    {
      "name": "initializeUserAccount",
      "accounts": [
        {
          "name": "payer",
          "isMut": true,
          "isSigner": true
        },
        {
          "name": "authority",
          "isMut": false,
          "isSigner": true
        },
        {
          "name": "globalTreasurySigner",
          "isMut": true,
          "isSigner": false
        },
        {
          "name": "owner",
          "isMut": false,
          "isSigner": false
        },
        {
          "name": "mint",
          "isMut": false,
          "isSigner": false
        },
        {
          "name": "userStateSigner",
          "isMut": true,
          "isSigner": false
        },
        {
          "name": "systemProgram",
          "isMut": false,
          "isSigner": false
        }
      ],
      "args": [
        {
          "name": "rewardAmount",
          "type": "u64"
        }
      ]
    },
    {
      "name": "updateUserAccount",
      "accounts": [
        {
          "name": "payer",
          "isMut": true,
          "isSigner": true
        },
        {
          "name": "authority",
          "isMut": false,
          "isSigner": true
        },
        {
          "name": "globalTreasurySigner",
          "isMut": true,
          "isSigner": false
        },
        {
          "name": "owner",
          "isMut": false,
          "isSigner": false
        },
        {
          "name": "mint",
          "isMut": false,
          "isSigner": false
        },
        {
          "name": "userStateSigner",
          "isMut": true,
          "isSigner": false
        }
      ],
      "args": [
        {
          "name": "rewardAmount",
          "type": "u64"
        },
        {
          "name": "isClaimable",
          "type": "bool"
        }
      ]
    },
    {
      "name": "claimRewards",
      "accounts": [
        {
          "name": "user",
          "isMut": true,
          "isSigner": true
        },
        {
          "name": "globalTreasurySigner",
          "isMut": true,
          "isSigner": false
        },
        {
          "name": "mint",
          "isMut": false,
          "isSigner": false
        },
        {
          "name": "userStateSigner",
          "isMut": true,
          "isSigner": false
        },
        {
          "name": "sourceTokenAccount",
          "isMut": true,
          "isSigner": false
        },
        {
          "name": "destinationTokenAccount",
          "isMut": true,
          "isSigner": false
        },
        {
          "name": "systemProgram",
          "isMut": false,
          "isSigner": false
        },
        {
          "name": "tokenProgram",
          "isMut": false,
          "isSigner": false
        },
        {
          "name": "associatedTokenProgram",
          "isMut": false,
          "isSigner": false
        }
      ],
      "args": []
    }
  ],
  "accounts": [
    {
      "name": "RaffleTreasuryState",
      "type": {
        "kind": "struct",
        "fields": [
          {
            "name": "bump",
            "type": "u8"
          },
          {
            "name": "authority",
            "type": "publicKey"
          }
        ]
      }
    },
    {
      "name": "RaffleUserState",
      "type": {
        "kind": "struct",
        "fields": [
          {
            "name": "bump",
            "type": "u8"
          },
          {
            "name": "owner",
            "type": "publicKey"
          },
          {
            "name": "mint",
            "type": "publicKey"
          },
          {
            "name": "claimableAmount",
            "type": "u64"
          },
          {
            "name": "isClaimable",
            "type": "bool"
          }
        ]
      }
    }
  ],
  "errors": [
    {
      "code": 6000,
      "name": "PrizeNotClaimable",
      "msg": "Prize is not claimable"
    },
    {
      "code": 6001,
      "name": "AmountShouldBeGreaterThanZero",
      "msg": "Prize claim amount should be greater than zero"
    },
    {
      "code": 6002,
      "name": "PrizeAmountGreaterThanSourceAccountBalance",
      "msg": "Prize claim amount should be not be greater than source token account balance"
    }
  ],
  "metadata": {
    "address": "3sFaV13movRZYWj33zLxgHDqU89V3F1VZw7cGTktE5LR"
  }
}
